kcrw/apple_news/__init__.py
kcrw/apple_news/api.py
kcrw/apple_news/command.py
kcrw.apple_news-0.2.5.post1.dist-info/AUTHORS.rst
kcrw.apple_news-0.2.5.post1.dist-info/LICENSE
kcrw.apple_news-0.2.5.post1.dist-info/METADATA
kcrw.apple_news-0.2.5.post1.dist-info/WHEEL
kcrw.apple_news-0.2.5.post1.dist-info/entry_points.txt
kcrw.apple_news-0.2.5.post1.dist-info/top_level.txt
kcrw.apple_news-0.2.5.post1.dist-info/RECORD
