Metadata-Version: 2.1
Name: kcrw.apple-news
Version: 0.2.5.post1
Summary: Library for using the Apple News API
Home-page: https://github.com/KCRW-org/kcrw.apple_news
Author: Alec Mitchell
Author-email: alecpm@gmail.com
License: MIT license
Keywords: Apple News,REST API,KCRW
Platform: UNKNOWN
Classifier: Development Status :: 3 - Alpha
Classifier: Intended Audience :: Developers
Classifier: License :: OSI Approved :: MIT License
Classifier: Natural Language :: English
Classifier: Programming Language :: Python :: 2
Classifier: Programming Language :: Python :: 2.7
Classifier: Programming Language :: Python :: 3
Classifier: Programming Language :: Python :: 3.5
Classifier: Programming Language :: Python :: 3.6
Classifier: Programming Language :: Python :: 3.7
Classifier: Programming Language :: Python :: 3.8
Requires-Dist: requests[security]
Requires-Dist: six
Requires-Dist: Click
Requires-Dist: click-log
